azcam_webtools/__init__.py
azcam_webtools/exptool/__init__.py
azcam_webtools/exptool/exptool.html
azcam_webtools/exptool/exptool.js
azcam_webtools/exptool/exptool.py
azcam_webtools/exptool/style_exptool.css
azcam_webtools/status/__init__.py
azcam_webtools/status/status.html
azcam_webtools/status/status.js
azcam_webtools/status/status.py
azcam_webtools/status/style_status.css
azcam_webtools/webserver/__init__.py
azcam_webtools/webserver/fastapi_server.py
azcam_webtools/webserver/favicon.ico
azcam_webtools/webserver/test_api.py
azcam_webtools-24.0.dist-info/LICENSE
azcam_webtools-24.0.dist-info/WHEEL
azcam_webtools-24.0.dist-info/METADATA
azcam_webtools-24.0.dist-info/RECORD
