Metadata-Version: 2.1
Name: azcam-webtools
Version: 24.0
Summary: A azcam web application for interacting with azcamserver.
Keywords: ccd,imaging,astronomy,sensors
Author: Michael Lesser
Author-email: mlesser@arizona.edu
Requires-Dist: azcam
Requires-Dist: fastapi
Project-URL: Documentation, https://azcam.readthedocs.io/
Project-URL: Repository, https://github.com/mplesser/azcam-webtools/
